MS7_Uart_Loading/i2s_rx.v
module i2s_rx (
    input wire clk,             // System clock
    input wire rst_n,           // Active-low reset
    input wire rx,              // I2S receive input
    output reg  ws,
    output reg i2s_clk,
    output reg [63:0] rx_data  // Received data
);

    //I2S Receiver States
    parameter STATE_IDLE  = 2'b00;
    parameter RIGHT_STEREO = 2'b01;
    parameter LEFT_STEREO  = 2'b10;


    reg [1:0] state;
    reg [5:0] bit_idx;
    reg [63:0] rx_shift_reg;
    reg clk_count; 

// Clock divider (4MHz)
always @(posedge clk or negedge rst_n) begin
    if (!rst_n) begin
        clk_count <= 0;
        i2s_clk <= 0;
    end else begin
        if (clk_count == 1) begin
            i2s_clk <= ~i2s_clk; 
            clk_count <= 0;
        end else begin
            clk_count <= clk_count + 1;
        end
    end
end


    always @(posedge i2s_clk or negedge rst_n) begin
        if (!rst_n) begin
            state         <= STATE_IDLE;
            bit_idx       <= 6'b0;
            rx_shift_reg  <= 64'b0;
            rx_data       <= 32'b0;
            ws <= 1;


        end else begin
            case (state)
                RIGHT_STEREO: begin
                    ws <= 1'b1;
                    if (bit_idx >= 31) begin
                    bit_idx <= bit_idx + 1;
                    rx_data[31:0]       <= rx_shift_reg[31:0];
                    state <= LEFT_STEREO;
                    rx_shift_reg[31:0]  <= 32'd0;
                    end else begin
                            rx_shift_reg[bit_idx] <= rx;
                            bit_idx <= bit_idx + 1;
                            if(bit_idx>=24)
                            rx_shift_reg[bit_idx] <= 1'b0;
                    end
                
                end
                LEFT_STEREO: begin
                    ws <= 1'b0;
                    if (bit_idx >= 63) begin
                    rx_data[63:32]       <= rx_shift_reg[63:32];
                    state <= RIGHT_STEREO;
                    rx_shift_reg[63:32]  <= 32'd0;
                    bit_idx <= 6'b0;
                    end else begin
                            rx_shift_reg[bit_idx] <= rx;
                            bit_idx <= bit_idx + 1;
                            if(bit_idx>=56)
                            rx_shift_reg[bit_idx] <= 1'b0;
                    end
                end 
                STATE_IDLE: begin
                     state    <= RIGHT_STEREO;
                end
                default: state <= STATE_IDLE;
            endcase
        end
    end

endmodule

MS6/Hazard2_SoC_tb.v
module i2s_rx_tb;

    localparam SIMTIME = 100_000; // Simulation time

    reg clk;
    reg rst_n;
    reg rx;
    wire ws;
    wire i2s_clk;
    wire [63:0] rx_data;

    // clock
    initial clk = 0;
    always #5 clk = ~clk;

    // Reset
    initial begin
        rst_n = 0;
        #20; // Assert reset for a short period
        @(posedge clk);
        rst_n = 1;
    end

    // TB infrastructure
    initial begin
        $dumpfile("i2s_rx_tb.vcd");
        $dumpvars(0, i2s_rx_tb);
        #SIMTIME;
        $display("TB: Test Failed: Timeout");
        $finish;
    end

    // Instantiate the I2S Receiver
    i2s_rx uut (
        .clk(clk),
        .rst_n(rst_n),
        .rx(rx),
        .ws(ws),
        .i2s_clk(i2s_clk),
        .rx_data(rx_data)
    );

    // Test case: Generate I2S data stream
    initial begin
        // Initialize signals
        rx = 0;

        @(posedge rst_n);
        #50;

        // Example I2S data stream for two 32-bit stereo samples
        send_i2s_data(64'h55667788ABCDEFAB); 
        #10
        send_i2s_data(64'h22334455FBABABAB);
        #10
        send_i2s_data(64'hBABABABA55667788);
        #10
        send_i2s_data(64'h55667788ABCDEFAB);
        #100;

        #SIMTIME;
        $display("TB: Test Failed: Timeout");
        $finish;
    end

    // Task to send I2S data
    task send_i2s_data(input [63:0] data);
        integer i;
        begin
            for (i = 0; i < 64; i = i + 1) begin
                @(posedge i2s_clk);
                if(ws==1 && i>0 && i<32) 
                rx = data[i];
                else if(ws==0 && i>32 && i<64) 
                rx = data[i];  
            end
        end
    endtask

    // Monitor to check the received data and stop the simulation on a specific condition
    always @ (posedge i2s_clk) begin
        if (rx_data == 64'h0066778800CDEFAB) begin
            $display("TB: Test Passed: Received correct data");
            $finish;
        end
        if (rx_data == 64'h0033445500ABABAB) begin
            $display("TB: Test Passed: Received correct data");
            $finish;
        end
        if (rx_data == 64'h00BABABA00667788) begin
            $display("TB: Test Passed: Received correct data");
            $finish;
        end
        if (rx_data == 64'h0066778800CDEFAB) begin
            $display("TB: Test Passed: Received correct data");
            $finish;
        end


    end

endmodule

MS7/i2s_rx_tb.vcd
$date
	Wed Oct 23 04:43:25 2024
$end
$version
	Icarus Verilog
$end
$timescale
	1s
$end
$scope module i2s_rx_tb $end
$var wire 1 ! ws $end
$var wire 64 " rx_data [63:0] $end
$var wire 1 # i2s_clk $end
$var parameter 32 $ SIMTIME $end
$var reg 1 % clk $end
$var reg 1 & rst_n $end
$var reg 1 ' rx $end
$scope module uut $end
$var wire 1 % clk $end
$var wire 1 & rst_n $end
$var wire 1 ' rx $end
$var parameter 2 ( LEFT_STEREO $end
$var parameter 2 ) RIGHT_STEREO $end
$var parameter 2 * STATE_IDLE $end
$var reg 6 + bit_idx [5:0] $end
$var reg 1 , clk_count $end
$var reg 1 # i2s_clk $end
$var reg 64 - rx_data [63:0] $end
$var reg 64 . rx_shift_reg [63:0] $end
$var reg 2 / state [1:0] $end
$var reg 1 ! ws $end
$upscope $end
$scope task send_i2s_data $end
$var reg 64 0 data [63:0] $end
$var integer 32 1 i [31:0] $end
$upscope $end
$upscope $end
$enddefinitions $end
$comment Show the parameter values. $end
$dumpall
b0 *
b1 )
b10 (
b11000011010100000 $
$end
#0
$dumpvars
bx 1
bx 0
b0 /
b0 .
b0 -
0,
b0 +
0'
0&
0%
0#
b0 "
1!
$end
#5
1%
#10
0%
#15
1%
#20
0%
#25
1,
1&
1%
#30
0%
#35
b1 /
0,
1#
1%
#40
0%
#45
1,
1%
#50
0%
#55
0,
0#
1%
#60
0%
#65
1,
1%
#70
0%
#75
b1 +
b1 .
1'
0,
1#
1%
b1 1
b101010101100110011101111000100010101011110011011110111110101011 0
#80
0%
#85
1,
1%
#90
0%
#95
0,
0#
1%
#100
0%
#105
1,
1%
#110
0%
#115
b10 +
b11 .
b10 1
0,
1#
1%
#120
0%
#125
1,
1%
#130
0%
#135
0,
0#
1%
#140
0%
#145
1,
1%
#150
0%
#155
b11 +
b11 1
0'
0,
1#
1%
#160
0%
#165
1,
1%
#170
0%
#175
0,
0#
1%
#180
0%
#185
1,
1%
#190
0%
#195
b100 +
b1011 .
b100 1
1'
0,
1#
1%
#200
0%
#205
1,
1%
#210
0%
#215
0,
0#
1%
#220
0%
#225
1,
1%
#230
0%
#235
b101 +
b101 1
0'
0,
1#
1%
#240
0%
#245
1,
1%
#250
0%
#255
0,
0#
1%
#260
0%
#265
1,
1%
#270
0%
#275
b110 +
b101011 .
b110 1
1'
0,
1#
1%
#280
0%
#285
1,
1%
#290
0%
#295
0,
0#
1%
#300
0%
#305
1,
1%
#310
0%
#315
b111 +
b111 1
0'
0,
1#
1%
#320
0%
#325
1,
1%
#330
0%
#335
0,
0#
1%
#340
0%
#345
1,
1%
#350
0%
#355
b1000 +
b10101011 .
b1000 1
1'
0,
1#
1%
#360
0%
#365
1,
1%
#370
0%
#375
0,
0#
1%
#380
0%
#385
1,
1%
#390
0%
#395
b1001 +
b110101011 .
b1001 1
0,
1#
1%
#400
0%
#405
1,
1%
#410
0%
#415
0,
0#
1%
#420
0%
#425
1,
1%
#430
0%
#435
b1010 +
b1110101011 .
b1010 1
0,
1#
1%
#440
0%
#445
1,
1%
#450
0%
#455
0,
0#
1%
#460
0%
#465
1,
1%
#470
0%
#475
b1011 +
b11110101011 .
b1011 1
0,
1#
1%
#480
0%
#485
1,
1%
#490
0%
#495
0,
0#
1%
#500
0%
#505
1,
1%
#510
0%
#515
b1100 +
b111110101011 .
b1100 1
0,
1#
1%
#520
0%
#525
1,
1%
#530
0%
#535
0,
0#
1%
#540
0%
#545
1,
1%
#550
0%
#555
b1101 +
b1101 1
0'
0,
1#
1%
#560
0%
#565
1,
1%
#570
0%
#575
0,
0#
1%
#580
0%
#585
1,
1%
#590
0%
#595
b1110 +
b10111110101011 .
b1110 1
1'
0,
1#
1%
#600
0%
#605
1,
1%
#610
0%
#615
0,
0#
1%
#620
0%
#625
1,
1%
#630
0%
#635
b1111 +
b110111110101011 .
b1111 1
0,
1#
1%
#640
0%
#645
1,
1%
#650
0%
#655
0,
0#
1%
#660
0%
#665
1,
1%
#670
0%
#675
b10000 +
b1110111110101011 .
b10000 1
0,
1#
1%
#680
0%
#685
1,
1%
#690
0%
#695
0,
0#
1%
#700
0%
#705
1,
1%
#710
0%
#715
b10001 +
b11110111110101011 .
b10001 1
0,
1#
1%
#720
0%
#725
1,
1%
#730
0%
#735
0,
0#
1%
#740
0%
#745
1,
1%
#750
0%
#755
b10010 +
b10010 1
0'
0,
1#
1%
#760
0%
#765
1,
1%
#770
0%
#775
0,
0#
1%
#780
0%
#785
1,
1%
#790
0%
#795
b10011 +
b1011110111110101011 .
b10011 1
1'
0,
1#
1%
#800
0%
#805
1,
1%
#810
0%
#815
0,
0#
1%
#820
0%
#825
1,
1%
#830
0%
#835
b10100 +
b11011110111110101011 .
b10100 1
0,
1#
1%
#840
0%
#845
1,
1%
#850
0%
#855
0,
0#
1%
#860
0%
#865
1,
1%
#870
0%
#875
b10101 +
b10101 1
0'
0,
1#
1%
#880
0%
#885
1,
1%
#890
0%
#895
0,
0#
1%
#900
0%
#905
1,
1%
#910
0%
#915
b10110 +
b10110 1
0,
1#
1%
#920
0%
#925
1,
1%
#930
0%
#935
0,
0#
1%
#940
0%
#945
1,
1%
#950
0%
#955
b10111 +
b10011011110111110101011 .
b10111 1
1'
0,
1#
1%
#960
0%
#965
1,
1%
#970
0%
#975
0,
0#
1%
#980
0%
#985
1,
1%
#990
0%
#995
b11000 +
b110011011110111110101011 .
b11000 1
0,
1#
1%
#1000
0%
#1005
1,
1%
#1010
0%
#1015
0,
0#
1%
#1020
0%
#1025
1,
1%
#1030
0%
#1035
b11001 +
b110011011110111110101011 .
b11001 1
0,
1#
1%
#1040
0%
#1045
1,
1%
#1050
0%
#1055
0,
0#
1%
#1060
0%
#1065
1,
1%
#1070
0%
#1075
b11010 +
b110011011110111110101011 .
b11010 1
0,
1#
1%
#1080
0%
#1085
1,
1%
#1090
0%
#1095
0,
0#
1%
#1100
0%
#1105
1,
1%
#1110
0%
#1115
b11011 +
b11011 1
0'
0,
1#
1%
#1120
0%
#1125
1,
1%
#1130
0%
#1135
0,
0#
1%
#1140
0%
#1145
1,
1%
#1150
0%
#1155
b11100 +
b110011011110111110101011 .
b11100 1
1'
0,
1#
1%
#1160
0%
#1165
1,
1%
#1170
0%
#1175
0,
0#
1%
#1180
0%
#1185
1,
1%
#1190
0%
#1195
b11101 +
b11101 1
0'
0,
1#
1%
#1200
0%
#1205
1,
1%
#1210
0%
#1215
0,
0#
1%
#1220
0%
#1225
1,
1%
#1230
0%
#1235
b11110 +
b110011011110111110101011 .
b11110 1
1'
0,
1#
1%
#1240
0%
#1245
1,
1%
#1250
0%
#1255
0,
0#
1%
#1260
0%
#1265
1,
1%
#1270
0%
#1275
b11111 +
b11111 1
0'
0,
1#
1%
#1280
0%
#1285
1,
1%
#1290
0%
#1295
0,
0#
1%
#1300
0%
#1305
1,
1%
#1310
0%
#1315
b0 .
b10 /
b110011011110111110101011 "
b110011011110111110101011 -
b100000 +
b100000 1
1'
0,
1#
1%
#1320
0%
#1325
1,
1%
#1330
0%
#1335
0,
0#
1%
#1340
0%
#1345
1,
1%
#1350
0%
#1355
b100001 +
0!
b100001 1
0'
0,
1#
1%
#1360
0%
#1365
1,
1%
#1370
0%
#1375
0,
0#
1%
#1380
0%
#1385
1,
1%
#1390
0%
#1395
b100010 +
b100010 1
0,
1#
1%
#1400
0%
#1405
1,
1%
#1410
0%
#1415
0,
0#
1%
#1420
0%
#1425
1,
1%
#1430
0%
#1435
b100011 +
b100011 1
0,
1#
1%
#1440
0%
#1445
1,
1%
#1450
0%
#1455
0,
0#
1%
#1460
0%
#1465
1,
1%
#1470
0%
#1475
b100100 +
b100000000000000000000000000000000000 .
b100100 1
1'
0,
1#
1%
#1480
0%
#1485
1,
1%
#1490
0%
#1495
0,
0#
1%
#1500
0%
#1505
1,
1%
#1510
0%
#1515
b100101 +
b100101 1
0'
0,
1#
1%
#1520
0%
#1525
1,
1%
#1530
0%
#1535
0,
0#
1%
#1540
0%
#1545
1,
1%
#1550
0%
#1555
b100110 +
b100110 1
0,
1#
1%
#1560
0%
#1565
1,
1%
#1570
0%
#1575
0,
0#
1%
#1580
0%
#1585
1,
1%
#1590
0%
#1595
b100111 +
b100111 1
0,
1#
1%
#1600
0%
#1605
1,
1%
#1610
0%
#1615
0,
0#
1%
#1620
0%
#1625
1,
1%
#1630
0%
#1635
b101000 +
b1000100000000000000000000000000000000000 .
b101000 1
1'
0,
1#
1%
#1640
0%
#1645
1,
1%
#1650
0%
#1655
0,
0#
1%
#1660
0%
#1665
1,
1%
#1670
0%
#1675
b101001 +
b11000100000000000000000000000000000000000 .
b101001 1
0,
1#
1%
#1680
0%
#1685
1,
1%
#1690
0%
#1695
0,
0#
1%
#1700
0%
#1705
1,
1%
#1710
0%
#1715
b101010 +
b111000100000000000000000000000000000000000 .
b101010 1
0,
1#
1%
#1720
0%
#1725
1,
1%
#1730
0%
#1735
0,
0#
1%
#1740
0%
#1745
1,
1%
#1750
0%
#1755
b101011 +
b1111000100000000000000000000000000000000000 .
b101011 1
0,
1#
1%
#1760
0%
#1765
1,
1%
#1770
0%
#1775
0,
0#
1%
#1780
0%
#1785
1,
1%
#1790
0%
#1795
b101100 +
b101100 1
0'
0,
1#
1%
#1800
0%
#1805
1,
1%
#1810
0%
#1815
0,
0#
1%
#1820
0%
#1825
1,
1%
#1830
0%
#1835
b101101 +
b101111000100000000000000000000000000000000000 .
b101101 1
1'
0,
1#
1%
#1840
0%
#1845
1,
1%
#1850
0%
#1855
0,
0#
1%
#1860
0%
#1865
1,
1%
#1870
0%
#1875
b101110 +
b1101111000100000000000000000000000000000000000 .
b101110 1
0,
1#
1%
#1880
0%
#1885
1,
1%
#1890
0%
#1895
0,
0#
1%
#1900
0%
#1905
1,
1%
#1910
0%
#1915
b101111 +
b11101111000100000000000000000000000000000000000 .
b101111 1
0,
1#
1%
#1920
0%
#1925
1,
1%
#1930
0%
#1935
0,
0#
1%
#1940
0%
#1945
1,
1%
#1950
0%
#1955
b110000 +
b110000 1
0'
0,
1#
1%
#1960
0%
#1965
1,
1%
#1970
0%
#1975
0,
0#
1%
#1980
0%
#1985
1,
1%
#1990
0%
#1995
b110001 +
b110001 1
0,
1#
1%
#2000
0%
#2005
1,
1%
#2010
0%
#2015
0,
0#
1%
#2020
0%
#2025
1,
1%
#2030
0%
#2035
b110010 +
b10011101111000100000000000000000000000000000000000 .
b110010 1
1'
0,
1#
1%
#2040
0%
#2045
1,
1%
#2050
0%
#2055
0,
0#
1%
#2060
0%
#2065
1,
1%
#2070
0%
#2075
b110011 +
b110011101111000100000000000000000000000000000000000 .
b110011 1
0,
1#
1%
#2080
0%
#2085
1,
1%
#2090
0%
#2095
0,
0#
1%
#2100
0%
#2105
1,
1%
#2110
0%
#2115
b110100 +
b110100 1
0'
0,
1#
1%
#2120
0%
#2125
1,
1%
#2130
0%
#2135
0,
0#
1%
#2140
0%
#2145
1,
1%
#2150
0%
#2155
b110101 +
b110101 1
0,
1#
1%
#2160
0%
#2165
1,
1%
#2170
0%
#2175
0,
0#
1%
#2180
0%
#2185
1,
1%
#2190
0%
#2195
b110110 +
b100110011101111000100000000000000000000000000000000000 .
b110110 1
1'
0,
1#
1%
#2200
0%
#2205
1,
1%
#2210
0%
#2215
0,
0#
1%
#2220
0%
#2225
1,
1%
#2230
0%
#2235
b110111 +
b1100110011101111000100000000000000000000000000000000000 .
b110111 1
0,
1#
1%
#2240
0%
#2245
1,
1%
#2250
0%
#2255
0,
0#
1%
#2260
0%
#2265
1,
1%
#2270
0%
#2275
b111000 +
b111000 1
0'
0,
1#
1%
#2280
0%
#2285
1,
1%
#2290
0%
#2295
0,
0#
1%
#2300
0%
#2305
1,
1%
#2310
0%
#2315
b111001 +
b1100110011101111000100000000000000000000000000000000000 .
b111001 1
1'
0,
1#
1%
#2320
0%
#2325
1,
1%
#2330
0%
#2335
0,
0#
1%
#2340
0%
#2345
1,
1%
#2350
0%
#2355
b111010 +
b111010 1
0'
0,
1#
1%
#2360
0%
#2365
1,
1%
#2370
0%
#2375
0,
0#
1%
#2380
0%
#2385
1,
1%
#2390
0%
#2395
b111011 +
b1100110011101111000100000000000000000000000000000000000 .
b111011 1
1'
0,
1#
1%
#2400
0%
#2405
1,
1%
#2410
0%
#2415
0,
0#
1%
#2420
0%
#2425
1,
1%
#2430
0%
#2435
b111100 +
b111100 1
0'
0,
1#
1%
#2440
0%
#2445
1,
1%
#2450
0%
#2455
0,
0#
1%
#2460
0%
#2465
1,
1%
#2470
0%
#2475
b111101 +
b1100110011101111000100000000000000000000000000000000000 .
b111101 1
1'
0,
1#
1%
#2480
0%
#2485
1,
1%
#2490
0%
#2495
0,
0#
1%
#2500
0%
#2505
1,
1%
#2510
0%
#2515
b111110 +
b111110 1
0'
0,
1#
1%
#2520
0%
#2525
1,
1%
#2530
0%
#2535
0,
0#
1%
#2540
0%
#2545
1,
1%
#2550
0%
#2555
b111111 +
b1100110011101111000100000000000000000000000000000000000 .
b111111 1
1'
0,
1#
1%
#2560
0%
#2565
1,
1%
#2570
0%
#2575
0,
0#
1%
#2580
0%
#2585
1,
1%
#2590
0%
#2595
b0 +
b0 .
b1 /
b1100110011101111000100000000000110011011110111110101011 "
b1100110011101111000100000000000110011011110111110101011 -
b1000000 1
0'
0,
1#
1%
#2600
0%
#2605
1,
1%
b0 1
b10001000110011010001000101010111111011101010111010101110101011 0
#2610
0%
#2615
0,
0#
1%
#2620
0%
#2625
1,
1%
#2630
0%
#2635
b1 +
b1 .
1!
b1 1
1'
0,
1#
1%
