MS4/uart_rx.v
module uart_rx (
    input wire          clk,
    input wire          rst_n,
    input wire          rx,
    input wire  [15:0]  baud_div,
    output reg [7:0]    data,
    output reg         done
);

    reg         run;
    reg [15:0]  baud_cntr;
    reg [9:0]   rx_reg;
    reg [3:0]   bit_cntr;
    reg         last;

    wire tick = (baud_cntr == 16'b0);

    always @(posedge clk or negedge rst_n) begin
        if (!rst_n) begin
            baud_cntr <= 16'hFFFF; 
        end else if (tick) begin
            baud_cntr <= baud_div;
        end else if (run) begin
            baud_cntr <= baud_cntr - 1'b1; 
        end
    end

    always @(posedge clk or negedge rst_n) begin
        if (!rst_n) begin
            run <= 1'b0;
            bit_cntr <= 4'b0;
            rx_reg <= 10'b1111111111; 
            done <= 1'b0;
            data <= 8'b0;
            last <= 1'b0;
        end else begin
            if (run) begin
                if (tick) begin
                    if (last) begin
                        data <= rx_reg[8:1]; 
                        done <= 1'b1; 
                        run <= 1'b0; 
                        last <= 1'b0;
                    end
                    else if (bit_cntr > 0) begin
                        rx_reg <= {rx, rx_reg[9:1]};
                        bit_cntr <= bit_cntr - 1'b1;
                        if (bit_cntr == 4'd1) begin
                            last <= 1'b1;
                        end
                    end
                    else if (bit_cntr == 4'd0) begin
                        if (~rx) begin
                            run <= 1'b1;  
                            bit_cntr <= 4'd9;
                        end
                    end
                end
            end else if (bit_cntr == 4'd0 && ~rx) begin
                run <= 1'b1; 
                baud_cntr <= baud_div;
            end else begin
                done <= 1'b0;
            end
        end
    end

endmodule

MS4/uart_tx.v
module uart_tx(
    input wire          clk,
    input wire          rst_n,
    input wire          en,
    input wire          start,
    input wire  [7:0]   data,
    input wire  [15:0]  baud_div,
    output wire         tx,
    output wire         done
);

    reg         run;
    wire        tick;
    reg [9:0]   tx_reg;
    reg [15:0]  baud_cntr;

    // baud rate counter enable/diable T-FF
    always @(posedge clk, negedge rst_n)
        if(!rst_n)
            run <= 1'b0;
        else
            if(start)
                run <= 'b1;
            else if(done)
                run <= 'b0;

    // the baud rate counter
    assign tick = (baud_cntr == 'b0);
    always @(posedge clk, negedge rst_n)
        if(!rst_n)
            baud_cntr <= 16'hFFFF;
        else
            if(tick | start)
                baud_cntr <= baud_div;
            else if(en & run)
                baud_cntr <= baud_cntr - 'b1;

    // the shift register
    always @(posedge clk, negedge rst_n)
        if(!rst_n)
            tx_reg <= 'h3FF;
        else 
            if(tick)
                tx_reg <= {1'b1, tx_reg[9:1]};
            else if(start)
                tx_reg <= {1'b1, data, 1'b0};

    // Bit Counter
    reg [3:0] bit_cntr;
    always @(posedge clk, negedge rst_n)
        if(!rst_n) 
            bit_cntr <= 'd10;
        else if(start)
            bit_cntr <= 'd10;
        else if(tick & ~done)
            bit_cntr <= bit_cntr - 'b1;

    assign done = (bit_cntr == 'h0);

    //dis wrong
    assign tx = tx_reg[1];

    //assign tx = tx_reg[0];

endmodule

MS7_Uart_Loading/uart_tx_rx_tb.v
module uart_tx_rx_tb;
    reg          clk = 0;
    reg          rst_n = 0;
    reg          en;
    reg          start;
    reg  [7:0]   data;
    reg  [15:0]  baud_div;
    wire         tx;         
    wire         done_tx;   

    uart_tx UTX (
        .clk(clk),
        .rst_n(rst_n),
        .en(en),
        .start(start),
        .data(data),
        .baud_div(baud_div),
        .tx(tx),
        .done(done_tx)
    );


    wire [7:0] received_data; 
    wire done_rx;         

    uart_rx URX (
        .clk(clk),
        .rst_n(rst_n),
        .rx(tx),            
        .baud_div(baud_div),
        .data(received_data),
        .done(done_rx)
    );

    always #10 clk = !clk; 

    initial begin
        #777;
        @(posedge clk);
        #1 rst_n = 1;
    end

    initial begin
        $dumpfile("uart_tx_rx_tb.vcd");
        $dumpvars;
    end

    initial begin
        en = 0;
        start = 0;
        wait(rst_n == 1'b1);
        @(posedge clk);
        en = 1;
        baud_div = 9;

        // Transmit characters
        putchar(8'hA5);
        putchar(8'hF0);
        
        #100;
        $finish;
    end
  
    task putchar;
        input [7:0] char;
        begin
            @(posedge clk);
            data = char; 
            @(posedge clk);
            start = 1; 
            @(posedge clk);
            start = 0;
            wait(done_tx == 1'b1); 
            wait(done_rx == 1'b1); 
            if (received_data == char) begin
                $display("Received data: 0x%X", received_data);
            end else begin
                $display("Error: Expected 0x%X, but received 0x%X", char, received_data);
            end
        end
    endtask

endmodule

MS5/uart_tx_rx_tb.vcd
$date
	Tue Oct  8 19:36:26 2024
$end
$version
	Icarus Verilog
$end
$timescale
	1s
$end
$scope module uart_tx_rx_tb $end
$var wire 1 ! tx $end
$var wire 8 " received_data [7:0] $end
$var wire 1 # done_tx $end
$var wire 1 $ done_rx $end
$var reg 16 % baud_div [15:0] $end
$var reg 1 & clk $end
$var reg 8 ' data [7:0] $end
$var reg 1 ( en $end
$var reg 1 ) rst_n $end
$var reg 1 * start $end
$scope module URX $end
$var wire 16 + baud_div [15:0] $end
$var wire 1 & clk $end
$var wire 1 ) rst_n $end
$var wire 1 , tick $end
$var wire 1 ! rx $end
$var reg 16 - baud_cntr [15:0] $end
$var reg 4 . bit_cntr [3:0] $end
$var reg 8 / data [7:0] $end
$var reg 1 $ done $end
$var reg 1 0 last $end
$var reg 1 1 run $end
$var reg 10 2 rx_reg [9:0] $end
$upscope $end
$scope module UTX $end
$var wire 16 3 baud_div [15:0] $end
$var wire 1 & clk $end
$var wire 8 4 data [7:0] $end
$var wire 1 ( en $end
$var wire 1 ) rst_n $end
$var wire 1 * start $end
$var wire 1 ! tx $end
$var wire 1 5 tick $end
$var wire 1 # done $end
$var reg 16 6 baud_cntr [15:0] $end
$var reg 4 7 bit_cntr [3:0] $end
$var reg 1 8 run $end
$var reg 10 9 tx_reg [9:0] $end
$upscope $end
$scope task putchar $end
$var reg 8 : char [7:0] $end
$upscope $end
$upscope $end
$enddefinitions $end
#0
$dumpvars
bx :
b1111111111 9
08
b1010 7
b1111111111111111 6
05
bx 4
bx 3
b1111111111 2
01
00
b0 /
b0 .
b1111111111111111 -
0,
bx +
0*
0)
0(
bx '
0&
bx %
0$
0#
b0 "
1!
$end
#10
1&
#20
0&
#30
1&
#40
0&
#50
1&
#60
0&
#70
1&
#80
0&
#90
1&
#100
0&
#110
1&
#120
0&
#130
1&
#140
0&
#150
1&
#160
0&
#170
1&
#180
0&
#190
1&
#200
0&
#210
1&
#220
0&
#230
1&
#240
0&
#250
1&
#260
0&
#270
1&
#280
0&
#290
1&
#300
0&
#310
1&
#320
0&
#330
1&
#340
0&
#350
1&
#360
0&
#370
1&
#380
0&
#390
1&
#400
0&
#410
1&
#420
0&
#430
1&
#440
0&
#450
1&
#460
0&
#470
1&
#480
0&
#490
1&
#500
0&
#510
1&
#520
0&
#530
1&
#540
0&
#550
1&
#560
0&
#570
1&
#580
0&
#590
1&
#600
0&
#610
1&
#620
0&
#630
1&
#640
0&
#650
1&
#660
0&
#670
1&
#680
0&
#690
1&
#700
0&
#710
1&
#720
0&
#730
1&
#740
0&
#750
1&
#760
0&
#770
1&
#780
0&
#790
1&
#791
1)
#800
0&
#810
b10100101 :
b1001 %
b1001 +
b1001 3
1(
1&
#820
0&
#830
b10100101 '
b10100101 4
1&
#840
0&
#850
0!
b1101001010 9
b1001 6
18
1*
1&
#860
0&
#870
b1000 6
b1001 -
11
0*
1&
#880
0&
#890
b1000 -
b111 6
1&
#900
0&
#910
b110 6
b111 -
1&
#920
0&
#930
b110 -
b101 6
1&
#940
0&
#950
b100 6
b101 -
1&
#960
0&
#970
b100 -
b11 6
1&
#980
0&
#990
b10 6
b11 -
1&
#1000
0&
#1010
b10 -
b1 6
1&
#1020
0&
#1030
15
b0 6
b1 -
1&
#1040
0&
#1050
1!
1,
b0 -
b1001 7
b1110100101 9
05
b1001 6
1&
#1060
0&
#1070
b1000 6
0,
b1001 -
1&
#1080
0&
#1090
b1000 -
b111 6
1&
#1100
0&
#1110
b110 6
b111 -
1&
#1120
0&
#1130
b110 -
b101 6
1&
#1140
0&
#1150
b100 6
b101 -
1&
#1160
0&
#1170
b100 -
b11 6
1&
#1180
0&
#1190
b10 6
b11 -
1&
#1200
0&
#1210
b10 -
b1 6
1&
#1220
0&
#1230
15
b0 6
b1 -
1&
#1240
0&
#1250
0!
1,
b0 -
b1000 7
b1111010010 9
05
b1001 6
1&
#1260
0&
#1270
b1000 6
0,
b1001 -
b1001 .
1&
#1280
0&
#1290
b1000 -
b111 6
1&
#1300
0&
#1310
b110 6
b111 -
1&
#1320
0&
#1330
b110 -
b101 6
1&
#1340
0&
#1350
b100 6
b101 -
1&
#1360
0&
#1370
b100 -
b11 6
1&
#1380
0&
#1390
b10 6
b11 -
1&
#1400
0&
#1410
b10 -
b1 6
1&
#1420
0&
#1430
15
b0 6
b1 -
1&
#1440
0&
#1450
1!
1,
b0 -
b111 7
b1111101001 9
05
b1001 6
1&
#1460
0&
#1470
b1000 6
0,
b1001 -
b1000 .
1&
#1480
0&
#1490
b1000 -
b111 6
1&
#1500
0&
#1510
b110 6
b111 -
1&
#1520
0&
#1530
b110 -
b101 6
1&
#1540
0&
#1550
b100 6
b101 -
1&
#1560
0&
#1570
b100 -
b11 6
1&
#1580
0&
#1590
b10 6
b11 -
1&
#1600
0&
#1610
b10 -
b1 6
1&
#1620
0&
#1630
15
b0 6
b1 -
1&
#1640
0&
#1650
0!
1,
b0 -
b110 7
b1111110100 9
05
b1001 6
1&
#1660
0&
#1670
b1000 6
0,
b1001 -
b111 .
b111111111 2
1&
#1680
0&
#1690
b1000 -
b111 6
1&
#1700
0&
#1710
b110 6
b111 -
1&
#1720
0&
#1730
b110 -
b101 6
1&
#1740
0&
#1750
b100 6
b101 -
1&
#1760
0&
#1770
b100 -
b11 6
1&
#1780
0&
#1790
b10 6
b11 -
1&
#1800
0&
#1810
b10 -
b1 6
1&
#1820
0&
#1830
15
b0 6
b1 -
1&
#1840
0&
#1850
1,
b0 -
b101 7
b1111111010 9
05
b1001 6
1&
#1860
0&
#1870
b1000 6
0,
b1001 -
b110 .
b11111111 2
1&
#1880
0&
#1890
b1000 -
b111 6
1&
#1900
0&
#1910
b110 6
b111 -
1&
#1920
0&
#1930
b110 -
b101 6
1&
#1940
0&
#1950
b100 6
b101 -
1&
#1960
0&
#1970
b100 -
b11 6
1&
#1980
0&
#1990
b10 6
b11 -
1&
#2000
0&
#2010
b10 -
b1 6
1&
#2020
0&
#2030
15
b0 6
b1 -
1&
#2040
0&
#2050
1!
1,
b0 -
b100 7
b1111111101 9
05
b1001 6
1&
#2060
0&
#2070
b1000 6
0,
b1001 -
b101 .
b1001111111 2
1&
#2080
0&
#2090
b1000 -
b111 6
1&
#2100
0&
#2110
b110 6
b111 -
1&
#2120
0&
#2130
b110 -
b101 6
1&
#2140
0&
#2150
b100 6
b101 -
1&
#2160
0&
#2170
b100 -
b11 6
1&
#2180
0&
#2190
b10 6
b11 -
1&
#2200
0&
#2210
b10 -
b1 6
1&
#2220
0&
#2230
15
b0 6
b1 -
1&
#2240
0&
#2250
0!
1,
b0 -
b11 7
b1111111110 9
05
b1001 6
1&
#2260
0&
#2270
b1000 6
0,
b1001 -
b100 .
b100111111 2
1&
#2280
0&
#2290
b1000 -
b111 6
1&
#2300
0&
#2310
b110 6
b111 -
1&
#2320
0&
#2330
b110 -
b101 6
1&
#2340
0&
#2350
b100 6
b101 -
1&
#2360
0&
#2370
b100 -
b11 6
1&
#2380
0&
#2390
b10 6
b11 -
1&
#2400
0&
#2410
b10 -
b1 6
1&
#2420
0&
#2430
15
b0 6
b1 -
1&
#2440
0&
#2450
1!
1,
b0 -
b10 7
b1111111111 9
05
b1001 6
1&
#2460
0&
#2470
b1000 6
0,
b1001 -
b11 .
b1010011111 2
1&
#2480
0&
#2490
b1000 -
b111 6
1&
#2500
0&
#2510
b110 6
b111 -
1&
#2520
0&
#2530
b110 -
b101 6
1&
#2540
0&
#2550
b100 6
b101 -
1&
#2560
0&
#2570
b100 -
b11 6
1&
#2580
0&
#2590
b10 6
b11 -
1&
#2600
0&
#2610
b10 -
b1 6
1&
#2620
0&
#2630
15
b0 6
b1 -
1&
#2640
0&
#2650
1,
b0 -
b1 7
05
b1001 6
1&
#2660
0&
#2670
b1000 6
0,
b1001 -
b10 .
b1101001111 2
1&
#2680
0&
#2690
b1000 -
b111 6
1&
#2700
0&
#2710
b110 6
b111 -
1&
#2720
0&
#2730
b110 -
b101 6
1&
#2740
0&
#2750
b100 6
b101 -
1&
#2760
0&
#2770
b100 -
b11 6
1&
#2780
0&
#2790
b10 6
b11 -
1&
#2800
0&
#2810
b10 -
b1 6
1&
#2820
0&
#2830
15
b0 6
b1 -
1&
#2840
0&
#2850
1,
b0 -
1#
b0 7
05
b1001 6
1&
#2860
0&
#2870
08
b1000 6
0,
b1001 -
b1 .
b1110100111 2
1&
#2880
0&
#2890
b1000 -
1&
#2900
0&
#2910
b111 -
1&
#2920
0&
#2930
b110 -
1&
#2940
0&
#2950
b101 -
1&
#2960
0&
#2970
b100 -
1&
#2980
0&
#2990
b11 -
1&
#3000
0&
#3010
b10 -
1&
#3020
0&
#3030
b1 -
1&
#3040
0&
#3050
1,
b0 -
1&
#3060
0&
#3070
0,
b1001 -
10
b0 .
b1111010011 2
1&
#3080
0&
#3090
b1000 -
1&
#3100
0&
#3110
b111 -
1&
#3120
0&
#3130
b110 -
1&
#3140
0&
#3150
b101 -
1&
#3160
0&
#3170
b100 -
1&
#3180
0&
#3190
b11 -
1&
#3200
0&
#3210
b10 -
1&
#3220
0&
#3230
b1 -
1&
#3240
0&
#3250
1,
b0 -
1&
#3260
0&
#3270
b11110000 :
0,
b1001 -
00
01
1$
b11101001 "
b11101001 /
1&
#3280
0&
#3290
0$
b11110000 '
b11110000 4
1&
#3300
0&
#3310
0!
18
b1001 6
b1111100000 9
0#
b1010 7
1*
1&
#3320
0&
#3330
11
b1000 6
0*
1&
#3340
0&
#3350
b111 6
b1000 -
1&
#3360
0&
#3370
b111 -
b110 6
1&
#3380
0&
#3390
b101 6
b110 -
1&
#3400
0&
#3410
b101 -
b100 6
1&
#3420
0&
#3430
b11 6
b100 -
1&
#3440
0&
#3450
b11 -
b10 6
1&
#3460
0&
#3470
b1 6
b10 -
1&
#3480
0&
#3490
b1 -
15
b0 6
1&
#3500
0&
#3510
05
b1001 6
b1111110000 9
b1001 7
1,
b0 -
1&
#3520
0&
#3530
b1001 .
0,
b1001 -
b1000 6
1&
#3540
0&
#3550
b111 6
b1000 -
1&
#3560
0&
#3570
b111 -
b110 6
1&
#3580
0&
#3590
b101 6
b110 -
1&
#3600
0&
#3610
b101 -
b100 6
1&
#3620
0&
#3630
b11 6
b100 -
1&
#3640
0&
#3650
b11 -
b10 6
1&
#3660
0&
#3670
b1 6
b10 -
1&
#3680
0&
#3690
b1 -
15
b0 6
1&
#3700
0&
#3710
05
b1001 6
b1111111000 9
b1000 7
1,
b0 -
1&
#3720
0&
#3730
b1000 .
b111101001 2
0,
b1001 -
b1000 6
1&
#3740
0&
#3750
b111 6
b1000 -
1&
#3760
0&
#3770
b111 -
b110 6
1&
#3780
0&
#3790
b101 6
b110 -
1&
#3800
0&
#3810
b101 -
b100 6
1&
#3820
0&
#3830
b11 6
b100 -
1&
#3840
0&
#3850
b11 -
b10 6
1&
#3860
0&
#3870
b1 6
b10 -
1&
#3880
0&
#3890
b1 -
15
b0 6
1&
#3900
0&
#3910
05
b1001 6
b1111111100 9
b111 7
1,
b0 -
1&
#3920
0&
#3930
b111 .
b11110100 2
0,
b1001 -
b1000 6
1&
#3940
0&
#3950
b111 6
b1000 -
1&
#3960
0&
#3970
b111 -
b110 6
1&
#3980
0&
#3990
b101 6
b110 -
1&
#4000
0&
#4010
b101 -
b100 6
1&
#4020
0&
#4030
b11 6
b100 -
1&
#4040
0&
#4050
b11 -
b10 6
1&
#4060
0&
#4070
b1 6
b10 -
1&
#4080
0&
#4090
b1 -
15
b0 6
1&
#4100
0&
#4110
05
b1001 6
b1111111110 9
b110 7
1,
b0 -
1&
#4120
0&
#4130
b110 .
b1111010 2
0,
b1001 -
b1000 6
1&
#4140
0&
#4150
b111 6
b1000 -
1&
#4160
0&
#4170
b111 -
b110 6
1&
#4180
0&
#4190
b101 6
b110 -
1&
#4200
0&
#4210
b101 -
b100 6
1&
#4220
0&
#4230
b11 6
b100 -
1&
#4240
0&
#4250
b11 -
b10 6
1&
#4260
0&
#4270
b1 6
b10 -
1&
#4280
0&
#4290
b1 -
15
b0 6
1&
#4300
0&
#4310
1!
05
b1001 6
b1111111111 9
b101 7
1,
b0 -
1&
#4320
0&
#4330
b101 .
b1000111101 2
0,
b1001 -
b1000 6
1&
#4340
0&
#4350
b111 6
b1000 -
1&
#4360
0&
#4370
b111 -
b110 6
1&
#4380
0&
#4390
b101 6
b110 -
1&
#4400
0&
#4410
b101 -
b100 6
1&
#4420
0&
#4430
b11 6
b100 -
1&
#4440
0&
#4450
b11 -
b10 6
1&
#4460
0&
#4470
b1 6
b10 -
1&
#4480
0&
#4490
b1 -
15
b0 6
1&
#4500
0&
#4510
05
b1001 6
b100 7
1,
b0 -
1&
#4520
0&
#4530
b100 .
b1100011110 2
0,
b1001 -
b1000 6
1&
#4540
0&
#4550
b111 6
b1000 -
1&
#4560
0&
#4570
b111 -
b110 6
1&
#4580
0&
#4590
b101 6
b110 -
1&
#4600
0&
#4610
b101 -
b100 6
1&
#4620
0&
#4630
b11 6
b100 -
1&
#4640
0&
#4650
b11 -
b10 6
1&
#4660
0&
#4670
b1 6
b10 -
1&
#4680
0&
#4690
b1 -
15
b0 6
1&
#4700
0&
#4710
05
b1001 6
b11 7
1,
b0 -
1&
#4720
0&
#4730
b11 .
b1110001111 2
0,
b1001 -
b1000 6
1&
#4740
0&
#4750
b111 6
b1000 -
1&
#4760
0&
#4770
b111 -
b110 6
1&
#4780
0&
#4790
b101 6
b110 -
1&
#4800
0&
#4810
b101 -
b100 6
1&
#4820
0&
#4830
b11 6
b100 -
1&
#4840
0&
#4850
b11 -
b10 6
1&
#4860
0&
#4870
b1 6
b10 -
1&
#4880
0&
#4890
b1 -
15
b0 6
1&
#4900
0&
#4910
05
b1001 6
b10 7
1,
b0 -
1&
#4920
0&
#4930
b10 .
b1111000111 2
0,
b1001 -
b1000 6
1&
#4940
0&
#4950
b111 6
b1000 -
1&
#4960
0&
#4970
b111 -
b110 6
1&
#4980
0&
#4990
b101 6
b110 -
1&
#5000
0&
#5010
b101 -
b100 6
1&
#5020
0&
#5030
b11 6
b100 -
1&
#5040
0&
#5050
b11 -
b10 6
1&
#5060
0&
#5070
b1 6
b10 -
1&
#5080
0&
#5090
b1 -
15
b0 6
1&
#5100
0&
#5110
05
b1001 6
b1 7
1,
b0 -
1&
#5120
0&
#5130
b1 .
b1111100011 2
0,
b1001 -
b1000 6
1&
#5140
0&
#5150
b111 6
b1000 -
1&
#5160
0&
#5170
b111 -
b110 6
1&
#5180
0&
#5190
b101 6
b110 -
1&
#5200
0&
#5210
b101 -
b100 6
1&
#5220
0&
#5230
b11 6
b100 -
1&
#5240
0&
#5250
b11 -
b10 6
1&
#5260
0&
#5270
b1 6
b10 -
1&
#5280
0&
#5290
b1 -
15
b0 6
1&
#5300
0&
#5310
05
b1001 6
1#
b0 7
1,
b0 -
1&
#5320
0&
#5330
10
b0 .
b1111110001 2
0,
b1001 -
b1000 6
08
1&
#5340
0&
#5350
b1000 -
1&
#5360
0&
#5370
b111 -
1&
#5380
0&
#5390
b110 -
1&
#5400
0&
#5410
b101 -
1&
#5420
0&
#5430
b100 -
1&
#5440
0&
#5450
b11 -
1&
#5460
0&
#5470
b10 -
1&
#5480
0&
#5490
b1 -
1&
#5500
0&
#5510
1,
b0 -
1&
#5520
0&
#5530
00
01
1$
b11111000 "
b11111000 /
0,
b1001 -
1&
#5540
0&
#5550
0$
1&
